ttl_dict/__init__.py
ttl_dict/py.typed
time_to_live_dict-0.1.4.dist-info/METADATA
time_to_live_dict-0.1.4.dist-info/WHEEL
time_to_live_dict-0.1.4.dist-info/licenses/LICENSE
time_to_live_dict-0.1.4.dist-info/RECORD
