Metadata-Version: 2.4
Name: time-to-live-dict
Version: 0.1.4
Project-URL: Repository, https://github.com/chuanconggao/TTLDict/
License-Expression: MIT
License-File: LICENSE
Requires-Python: >=3.12
